gradio_canvaworkflow/__init__.py
gradio_canvaworkflow/canvaworkflow.py
gradio_canvaworkflow/canvaworkflow.pyi
gradio_canvaworkflow/templates/component/index.js
gradio_canvaworkflow/templates/component/style.css
gradio_canvaworkflow/templates/example/index.js
gradio_canvaworkflow/templates/example/style.css
gradio_canvaworkflow-0.0.2.dist-info/METADATA
gradio_canvaworkflow-0.0.2.dist-info/WHEEL
gradio_canvaworkflow-0.0.2.dist-info/RECORD
